mkutils/__init__.py
mkutils/_multithread.py
mkutils/_show_images.py
mkutils/_to_pickle.py
mkutils/stutils.py
utils_mkmenta-0.0.1.dist-info/LICENSE.txt
utils_mkmenta-0.0.1.dist-info/METADATA
utils_mkmenta-0.0.1.dist-info/WHEEL
utils_mkmenta-0.0.1.dist-info/top_level.txt
utils_mkmenta-0.0.1.dist-info/RECORD
